server/__init__.py
server/constants.py
server/plugin.py
server/app/__init__.py
server/app/controllers/__init__.py
server/app/controllers/hierarchy.py
server/app/controllers/layout_hierarchy_controller.py
server/app/controllers/match_nodes_controller.py
server/app/model/__init__.py
server/app/model/hierarchy.py
server/app/model/layout_hierarchy_model.py
server/app/model/match_nodes_model.py
server/app/repositories/__init__.py
server/app/repositories/graph_repo_base.py
server/app/repositories/graph_repo_db.py
server/app/repositories/graph_repo_vis.py
server/app/service/__init__.py
server/app/service/graph_service.py
server/app/service/graph_service_base.py
server/app/service/graph_service_db.py
server/app/service/graph_service_factory.py
server/app/service/graph_service_vis.py
server/app/utils/__init__.py
server/app/utils/constant.py
server/app/utils/file_check_wrapper.py
server/app/utils/global_state.py
server/app/utils/graph_utils.py
server/app/utils/i18n.py
server/app/views/__init__.py
server/app/views/graph_views.py
server/static/index.html
server/static/index.js
tb_graph_ascend-8.2.0.dist-info/METADATA
tb_graph_ascend-8.2.0.dist-info/WHEEL
tb_graph_ascend-8.2.0.dist-info/entry_points.txt
tb_graph_ascend-8.2.0.dist-info/top_level.txt
tb_graph_ascend-8.2.0.dist-info/RECORD
