Metadata-Version: 2.4
Name: tb-graph-ascend
Version: 8.2.0
Summary: Model Hierarchical Visualization TensorBoard Plugin
Home-page: https://gitcode.com/Ascend/mstt/tree/master/plugins/tensorboard-plugins/tb_graph_ascend
Author: Ascend Team
Author-email: pmail_mindstudio@huawei.com
License: BSD-3
Keywords: tensorboard graph ascend plugin
Classifier: Intended Audience :: Developers
Classifier: Intended Audience :: Education
Classifier: Intended Audience :: Science/Research
Classifier: License :: OSI Approved :: BSD License
Classifier: Programming Language :: Python :: 3
Classifier: Topic :: Scientific/Engineering
Classifier: Topic :: Scientific/Engineering :: Mathematics
Classifier: Topic :: Scientific/Engineering :: Artificial Intelligence
Classifier: Topic :: Software Development
Classifier: Topic :: Software Development :: Libraries
Classifier: Topic :: Software Development :: Libraries :: Python Modules
Requires-Python: >=3.7
Requires-Dist: tensorboard>=2.11.2
Dynamic: author
Dynamic: author-email
Dynamic: classifier
Dynamic: description
Dynamic: home-page
Dynamic: keywords
Dynamic: license
Dynamic: requires-dist
Dynamic: requires-python
Dynamic: summary
